LICENSE
README.md
setup.py
epoch_converter_scraper/__init__.py
epoch_converter_scraper.egg-info/PKG-INFO
epoch_converter_scraper.egg-info/SOURCES.txt
epoch_converter_scraper.egg-info/dependency_links.txt
epoch_converter_scraper.egg-info/requires.txt
epoch_converter_scraper.egg-info/top_level.txt