Metadata-Version: 2.1
Name: epoch-converter-scraper
Version: 1.0.0
Summary: A python library to scrape epoch converter data
Home-page: UNKNOWN
Author: DataKund
Author-email: datakund@gmail.com
License: Apache License 2.0
Keywords: epoch converter scraper product python bot_studio automation
Platform: UNKNOWN
License-File: LICENSE
